sqlite_cache/__init__.py
sqlite_cache/sqlite_cache.py
python_sqlite_cache-0.0.2.dist-info/LICENSE
python_sqlite_cache-0.0.2.dist-info/METADATA
python_sqlite_cache-0.0.2.dist-info/WHEEL
python_sqlite_cache-0.0.2.dist-info/top_level.txt
python_sqlite_cache-0.0.2.dist-info/zip-safe
python_sqlite_cache-0.0.2.dist-info/RECORD
