Metadata-Version: 2.1
Name: python-sqlite-cache
Version: 0.0.2
Summary: SQLite cache for Python.
Home-page: https://github.com/csotelo/python-sqlite-cache
Author: Carlos Eduardo Sotelo Pinto
Author-email: UNKNOWN
License: UNKNOWN
Download-URL: http://pypi.python.org/python-sqlite-cache/
Keywords: sqlite cache
Platform: UNKNOWN
Classifier: Development Status :: 5 - Production/Stable
Classifier: Intended Audience :: Developers
Classifier: License :: OSI Approved :: MIT License
Classifier: Natural Language :: English
Classifier: Operating System :: OS Independent
Classifier: Programming Language :: Python
Classifier: Topic :: Software Development :: Libraries :: Python Modules
